Workbook

Sheet Tareas
A1: ENSAMBLA / PRODUCT BACKLOG · TAREAS
A2: Tu sistema, un bloque a la vez. | Tareas listas para el tablero, agrupadas por MVP e historia. Antes de agarrar una, fijate que sus dependencias estén hechas.
A4: TAREAS | C4: MVP 2 · CORE | D4: MVP 3 · MEJORAS | F4: MVP 4 · APP COMPLETA | G4: MVP 2 TERMINADAS | H4: TERMINADAS
A5: =COUNTA(A10:A400) | C5: =COUNTIF(B10:B400,"MVP 2") | D5: =COUNTIF(B10:B400,"MVP 3") | F5: =COUNTIF(B10:B400,"MVP 4") | G5: =COUNTIFS(B10:B400,"MVP 2",J10:J400,"Hecho") | H5: =COUNTIF(J10:J400,"Hecho")
A7: MVP 1 = pantallas (entregado). MVP 2 = core: foto del cuaderno → lectura con IA → revisión → registros ordenados, con interfaz accesible para personas mayores. MVP 3 = mejoras de uso, ABM de soporte, modo construir/usar e indicadores. MVP 4 = equipos, planes, importación de planillas, WhatsApp/audio, integraciones y analítica (app completa).
A8: Área: FE frontend · BE backend/API · BD base de datos · Infra · QA · Fullstack (tarea chica que toca front y back). Talle: S ≈ hasta 1 día · M ≈ 2-3 días · L ≈ 4+ días (conviene partirla). "Depende de" = tareas que tienen que estar hechas antes.
A9: ID | B9: MVP | C9: Historia | D9: Área | E9: Tarea | F9: Qué hay que hacer | G9: Criterio de hecho | H9: Depende de | I9: Talle | J9: Estado | K9: Responsable
A10: T-001 | B10: MVP 2 | C10: H-00 · Base técnica | D10: Infra | E10: Estructura del repositorio | F10: Repo con /web (React + TS) y /api, linter, formateador, .env.example, README con cómo levantar todo. | G10: Cualquiera clona, copia .env.example y levanta front y API con un comando. | H10: — | I10: S | J10: Por hacer
A11: T-002 | B11: MVP 2 | C11: H-00 · Base técnica | D11: Infra | E11: CI en pull requests | F11: Pipeline que corre lint, typecheck y tests en cada PR; bloquea el merge si falla. | G11: Un PR con error de lint no se puede mergear. | H11: T-001 | I11: S | J11: Por hacer
A12: T-003 | B12: MVP 2 | C12: H-00 · Base técnica | D12: Infra | E12: Docker y docker-compose local | F12: Dockerfile de web y api + docker-compose con base de datos. | G12: docker compose up levanta web, api y BD funcionando. | H12: T-001 | I12: S | J12: Por hacer
A13: T-004 | B13: MVP 2 | C13: H-00 · Base técnica | D13: BD | E13: Modelo de datos del core | F13: Tablas users, businesses, projects, blocks, fields (type, required, default, options JSON, position), records (values JSON, block_id, business_id, source_upload_id) y uploads (lote, fotos, estado, resultado de IA JSON) + migraciones. | G13: Migraciones corren de cero; diagrama del modelo en el repo. | H13: T-001 | I13: M | J13: Por hacer
A14: T-005 | B14: MVP 2 | C14: H-01 · Acceso y sesión | D14: BE | E14: Endpoint de registro | F14: POST /auth/register: valida datos, hashea contraseña, rechaza email repetido, crea usuario + negocio en una transacción. | G14: Registro válido → 201; email repetido → 409 con mensaje claro; contraseña nunca en texto plano. | H14: T-004 | I14: M | J14: Por hacer
A15: T-006 | B15: MVP 2 | C15: H-01 · Acceso y sesión | D15: BE | E15: Login, logout y sesión actual | F15: POST /auth/login, POST /auth/logout y GET /auth/me. Sesión por token/cookie httpOnly con expiración. | G15: Credenciales malas → 401; después del logout el token ya no sirve. | H15: T-005 | I15: M | J15: Por hacer
A16: T-007 | B16: MVP 2 | C16: H-01 · Acceso y sesión | D16: BE | E16: Middleware de autenticación | F16: Guard global que exige sesión válida en toda ruta salvo /auth/*. | G16: Cualquier endpoint privado sin sesión devuelve 401 (test automatizado). | H16: T-006 | I16: S | J16: Por hacer
A17: T-008 | B17: MVP 2 | C17: H-01 · Acceso y sesión | D17: FE | E17: Pantallas de login y registro | F17: Formularios conectados a la API con validación, errores del servidor y campo 'nombre del negocio' en el registro. | G17: Se registra, entra y ve el aviso si la contraseña es incorrecta. | H17: T-006 | I17: M | J17: Por hacer
A18: T-009 | B18: MVP 2 | C18: H-01 · Acceso y sesión | D18: FE | E18: Sesión en el cliente y rutas protegidas | F18: Contexto de usuario, redirección a login si no hay sesión, botón de cerrar sesión. | G18: Sin sesión, cualquier URL privada redirige a /login; logout vuelve a /login. | H18: T-008 | I18: S | J18: Por hacer
A19: T-010 | B19: MVP 2 | C19: H-02 · Espacio de negocio y aislamiento de datos | D19: BE | E19: Filtro por negocio en todas las consultas | F19: Middleware que toma el business_id de la sesión y capa de datos que lo aplica siempre (nunca desde el body/URL). | G19: No existe query a projects/blocks/fields/records sin business_id. | H19: T-007 | I19: M | J19: Por hacer
A20: T-011 | B20: MVP 2 | C20: H-02 · Espacio de negocio y aislamiento de datos | D20: QA | E20: Tests de aislamiento entre negocios | F20: Tests de API: usuario de negocio A intenta leer/editar/borrar recursos de B por id. | G20: Todos los intentos devuelven 404/403; tests en CI. | H20: T-010, T-027 | I20: S | J20: Por hacer
A21: T-077 | B21: MVP 2 | C21: H-28 · Subir fotos del cuaderno | D21: Infra | E21: Almacenamiento de archivos | F21: Bucket S3 compatible (MinIO en docker-compose local) con URLs firmadas para las fotos del cuaderno y futuros adjuntos. | G21: Los archivos no son accesibles sin URL firmada. | H21: T-003 | I21: S | J21: Por hacer
... A117: T-107 | B117: MVP 4 | C117: H-31 · Cargar por WhatsApp o audio | D117: Fullstack | E117: Carga por audio | F117: Grabar un audio corto, transcribirlo y extraer el registro con el servicio de IA para revisarlo y confirmarlo. | G117: Un audio tipo 'vendí 3 velas a Marta a 4500' genera un registro a confirmar con esos datos. | H117: T-095, T-101 | I117: L | J117: Por hacer

Sheet Historias
A1: HISTORIAS · agrupan las tareas del tablero
A2: "Tareas" y "Hechas" se calculan solas desde la hoja Tareas.
A4: ID | B4: MVP | C4: Módulo | D4: Historia | E4: Qué debe permitir | F4: Cómo comprobamos que está lista | G4: Tareas | H4: Hechas | I4: Agrupa (códigos anteriores) | J4: Por qué va en este MVP
A5: H-00 | B5: MVP 2 | C5: Base | D5: Base técnica | E5: Estructura, CI, contenedores y modelo de datos sobre el que se construye todo. | F5: — | G5: =COUNTIF(Tareas!$C$10:$C$400,"H-00 · Base técnica") | H5: =COUNTIFS(Tareas!$C$10:$C$400,"H-00 · Base técnica",Tareas!$J$10:$J$400,"Hecho") | I5: ENS-066 (parcial) | J5: Sin esto nadie puede empezar a codear.
A6: H-01 | B6: MVP 2 | C6: Acceso | D6: Acceso y sesión | E6: Registrarse, iniciar y cerrar sesión, y que las pantallas y datos privados solo se vean con sesión activa. | F6: • El registro no admite correos repetidos. • Contraseña incorrecta muestra aviso. • Al cerrar sesión las rutas privadas dejan de estar disponibles. • La API rechaza pedidos sin sesión válida. | G6: =COUNTIF(Tareas!$C$10:$C$400,"H-01 · Acceso y sesión") | H6: =COUNTIFS(Tareas!$C$10:$C$400,"H-01 · Acceso y sesión",Tareas!$J$10:$J$400,"Hecho") | I6: ENS-001, ENS-002, ENS-003, ENS-005 | J6: Sin usuario no hay sistema: es la puerta de entrada al core.
A7: H-02 | B7: MVP 2 | C7: Acceso | D7: Espacio de negocio y aislamiento de datos | E7: Crear el espacio del negocio al empezar (nombre y listo) y garantizar que cada negocio solo vea su propia información. | F7: • Al registrarse se crea o pide el espacio del negocio. • Toda consulta y modificación se filtra por el negocio del usuario. • Un usuario no puede acceder a datos de otro negocio ni forzando la URL o la API. | G7: =COUNTIF(Tareas!$C$10:$C$400,"H-02 · Espacio de negocio y aislamiento de datos") | H7: =COUNTIFS(Tareas!$C$10:$C$400,"H-02 · Espacio de negocio y aislamiento de datos",Tareas!$J$10:$J$400,"Hecho") | I7: ENS-006, ENS-041 | J7: Todo lo que se construye cuelga del negocio; el aislamiento es seguridad base, no se agrega después.
A8: H-28 | B8: MVP 2 | C8: Digitalizar | D8: Subir fotos del cuaderno | E8: Subir una o varias fotos de páginas del cuaderno desde la cámara del celular o la galería, verlas antes de enviar y guardarlas de forma privada en el negocio. | F8: • Se puede sacar la foto con la cámara o elegirla de la galería. • Se suben varias páginas juntas y se pueden rotar o quitar antes de enviar. • Solo se aceptan imágenes (JPG, PNG, HEIC) y PDF hasta el tamaño límite. • Las fotos solo las ve el negocio que las subió. | G8: =COUNTIF(Tareas!$C$10:$C$400,"H-28 · Subir fotos del cuaderno") | H8: =COUNTIFS(Tareas!$C$10:$C$400,"H-28 · Subir fotos del cuaderno",Tareas!$J$10:$J$400,"Hecho") | I8: Nuevo (v1.1) · ENS-027 (parcial) | J8: Es la puerta de entrada del core: sin foto no hay digitalización.
A9: H-29 | B9: MVP 2 | C9: Digitalizar | D9: Lectura del cuaderno con IA | E9: Procesar las fotos con un modelo de IA que reconozca el tipo de registro (ventas, gastos, pedidos, stock, fiados), proponga bloque y campos tipados y extraiga cada renglón con su nivel de confianza. | F9: • Con el set de fotos de prueba se alcanza la meta de precisión fijada tras el spike. • Cada dato extraído trae un nivel de confianza. • Si ya existe un bloque parecido, propone sumar los registros ahí. • El procesamiento corre en segundo plano con estados visibles. • El consumo de IA queda registrado y limitado por negocio. | G9: =COUNTIF(Tareas!$C$10:$C$400,"H-29 · Lectura del cuaderno con IA") | H9: =COUNTIFS(Tareas!$C$10:$C$400,"H-29 · Lectura del cuaderno con IA",Tareas!$J$10:$J$400,"Hecho") | I9: Nuevo (v1.1) | J9: Es la propuesta de valor: que el sistema se arme solo a partir de la foto.
A10: H-30 | B10: MVP 2 | C10: Digitalizar | D10: Revisar y confirmar lo que leyó la IA | E10: Mostrar la foto junto a los datos leídos, resaltar los dudosos, permitir corregir y ajustar la estructura propuesta, y al confirmar crear el bloque y los registros vinculados a su foto de origen. | F10: • En el celular se ve la foto y debajo los datos; en computadora, lado a lado. • Los datos con baja confianza aparecen resaltados. • Se pueden corregir celdas, quitar filas y renombrar campos antes de guardar. • Nada se guarda hasta confirmar; al confirmar se crea todo de una sola vez. • Desde la ficha de un registro se puede ver la foto de la que salió. | G10: =COUNTIF(Tareas!$C$10:$C$400,"H-30 · Revisar y confirmar lo que leyó la IA") | H10: =COUNTIFS(Tareas!$C$10:$C$400,"H-30 · Revisar y confirmar lo que leyó la IA",Tareas!$J$10:$J$400,"Hecho") | I10: Nuevo (v1.1) | J10: La revisión humana da confianza y corrige los errores de la IA; sin esto no se puede usar con datos reales.
A11: H-03 | B11: MVP 2 | C11: Crear proyecto | D11: Crear proyecto desde plantilla o en blanco | E11: Pantalla de inicio con tres caminos: «Subir foto de mi cuaderno» (principal), usar una plantilla base (inventario, pedidos, clientes) o arrancar un proyecto en blanco. | F11: • Sin proyectos, «Subir foto de mi cuaderno» es la opción destacada y las otras dos quedan como secundarias. • Cada plantilla explica para qué sirve. • La plantilla se copia al negocio y se edita sin tocar el original. • El proyecto en blanco indica cómo agregar el primer bloque. | G11: =COUNTIF(Tareas!$C$10:$C$400,"H-03 · Crear proyecto desde plantilla o en blanco") | H11: =COUNTIFS(Tareas!$C$10:$C$400,"H-03 · Crear proyecto desde plantilla o en blanco",Tareas!$J$10:$J$400,"Hecho") | I11: ENS-008, ENS-010, ENS-012, ENS-013 | J11: Camino alternativo para quien no tiene cuaderno o prefiere empezar de cero; la foto es la entrada principal.
A12: H-04 | B12: MVP 2 | C12: Constructor | D12: Constructor de bloques y campos | E12: Pantalla para armar el sistema: agregar, renombrar y eliminar bloques (Productos, Clientes, Pedidos…) y definir sus campos tipados con reglas básicas. | F12: • Tipos de campo: texto, número, fecha, opción y sí/no. • Se puede marcar un campo obligatorio y darle valor inicial. • Se pueden editar y borrar bloques y campos. • La estructura se guarda y sigue al reabrir el proyecto. | G12: =COUNTIF(Tareas!$C$10:$C$400,"H-04 · Constructor de bloques y campos") | H12: =COUNTIFS(Tareas!$C$10:$C$400,"H-04 · Constructor de bloques y campos",Tareas!$J$10:$J$400,"Hecho") | I12: ENS-015, ENS-016, ENS-017, ENS-018, ENS-021 | J12: La IA propone la estructura; el constructor permite corregirla o ampliarla. Se mantiene simple.
A13: H-05 | B13: MVP 2 | C13: Cargar datos | D13: Formulario de carga generado automáticamente | E13: Generar un formulario por bloque a partir de sus campos, validarlo (frontend y API) y guardar registros con avisos claros. | F13: • El formulario respeta los campos y tipos configurados. • Los errores aparecen junto al campo y explican qué corregir. • La API rechaza datos inválidos con mensajes comprensibles. • Un registro válido se guarda una sola vez y se confirma. • Ante un error no se pierde lo escrito. | G13: =COUNTIF(Tareas!$C$10:$C$400,"H-05 · Formulario de carga generado automáticamente") | H13: =COUNTIFS(Tareas!$C$10:$C$400,"H-05 · Formulario de carga generado automáticamente",Tareas!$J$10:$J$400,"Hecho") | I13: ENS-023, ENS-024, ENS-025, ENS-028, ENS-064 | J13: Permite cargar a mano lo que la foto no trae; reutiliza la misma validación que usa la digitalización.
A14: H-06 | B14: MVP 2 | C14: Consultar | D14: Tabla de registros con gestión completa | E14: Ver los registros de un bloque en una tabla, buscar y ordenar, abrir la ficha de un registro, editarlo y eliminarlo. | F14: • La tabla muestra las columnas del bloque. • La búsqueda filtra y las columnas se ordenan. • La ficha muestra todos los datos del registro. • Se edita y se ven los cambios guardados. • Eliminar pide confirmación. • Se ven totales de los campos numéricos y la cantidad de registros. | G14: =COUNTIF(Tareas!$C$10:$C$400,"H-06 · Tabla de registros con gestión completa") | H14: =COUNTIFS(Tareas!$C$10:$C$400,"H-06 · Tabla de registros con gestión completa",Tareas!$J$10:$J$400,"Hecho") | I14: ENS-026, ENS-029, ENS-030, ENS-031, ENS-033, Nuevo (v1.1) | J14: Cierra el ciclo de uso diario: ver lo que se digitalizó, buscar, corregir y saber cuánto suma.
A15: H-08 | B15: MVP 2 | C15: Usar | D15: Interfaz accesible para personas mayores | E15: Navegación consistente, diseño pensado para el celular y accesible para personas mayores (letra grande, botones amplios, contraste y lenguaje sin tecnicismos), con estados de vacío, carga y error en todas las pantallas del core. | F15: • Secciones y botones con nombres y ubicaciones consistentes. • Texto base de 18px o más y botones de 48px o más. • El flujo principal funciona en pantalla chica sin desbordes. • Ninguna pantalla queda en blanco: hay mensajes de vacío, carga y error. • Lighthouse accesibilidad ≥ 90 y personas mayores completan el flujo principal sin ayuda en la prueba. | G15: =COUNTIF(Tareas!$C$10:$C$400,"H-08 · Interfaz accesible para personas mayores") | H15: =COUNTIFS(Tareas!$C$10:$C$400,"H-08 · Interfaz accesible para personas mayores",Tareas!$J$10:$J$400,"Hecho") | I15: ENS-035, ENS-036, ENS-038, ENS-039, Nuevo (v1.1) | J15: El público son personas mayores: la accesibilidad es parte del core, no un pulido posterior.
A16: H-09 | B16: MVP 2 | C16: Calidad | D16: Despliegue y prueba del flujo principal | E16: Publicar Ensambla en un entorno accesible y probar de punta a punta el recorrido principal. | F16: • La app corre en un entorno público sin exponer claves ni contraseñas (variables de entorno). • Prueba E2E: registro → subir foto → revisar y corregir → confirmar → buscar el registro, sin errores. | G16: =COUNTIF(Tareas!$C$10:$C$400,"H-09 · Despliegue y prueba del flujo principal") | H16: =COUNTIFS(Tareas!$C$10:$C$400,"H-09 · Despliegue y prueba del flujo principal",Tareas!$J$10:$J$400,"Hecho") | I16: ENS-065, ENS-066 | J16: Sin deploy no hay demo ni venta; la prueba E2E asegura que el core no se rompe.
A17: H-07 | B17: MVP 3 | C17: Usar | D17: Modo construir / modo usar | E17: Separar la edición del sistema de su uso diario: alternar entre construir y usar (que funciona también como vista previa). | F17: • En modo usar no aparecen herramientas de construcción. • Desde el constructor se puede ver cómo queda y volver a editar. • Los cambios del constructor se reflejan al pasar a modo usar. | G17: =COUNTIF(Tareas!$C$10:$C$400,"H-07 · Modo construir / modo usar") | H17: =COUNTIFS(Tareas!$C$10:$C$400,"H-07 · Modo construir / modo usar",Tareas!$J$10:$J$400,"Hecho") | I17: ENS-022, ENS-050, ENS-051 | J17: Con la IA armando la estructura, la persona mayormente usa el sistema; separar construir/usar pasa a ser una mejora.
A18: H-10 | B18: MVP 3 | C18: Acceso | D18: Gestión de cuenta y negocio | E18: Recuperar la contraseña y editar los datos del negocio (nombre y datos básicos). | F18: • Llega un enlace temporal y se puede elegir contraseña nueva. • Los cambios del negocio se guardan y solo el dueño puede modificarlos. | G18: =COUNTIF(Tareas!$C$10:$C$400,"H-10 · Gestión de cuenta y negocio") | H18: =COUNTIFS(Tareas!$C$10:$C$400,"H-10 · Gestión de cuenta y negocio",Tareas!$J$10:$J$400,"Hecho") | I18: ENS-004, ENS-007 | J18: ABM de soporte: necesario para un producto en uso real, no para mostrar el core.
A19: H-11 | B19: MVP 3 | C19: Crear proyecto | D19: Plantillas y proyectos: vista previa y duplicado | E19: Revisar una plantilla antes de usarla y duplicar un proyecto existente. | F19: • La vista previa muestra las partes de la plantilla sin crear proyecto. • La copia de un proyecto se renombra y no arrastra los datos cargados. | G19: =COUNTIF(Tareas!$C$10:$C$400,"H-11 · Plantillas y proyectos: vista previa y duplicado") | H19: =COUNTIFS(Tareas!$C$10:$C$400,"H-11 · Plantillas y proyectos: vista previa y duplicado",Tareas!$J$10:$J$400,"Hecho") | I19: ENS-011, ENS-014 | J19: Mejora la experiencia de arranque una vez validado el core.
A20: H-12 | B20: MVP 3 | C20: Constructor | D20: Cambios seguros en la estructura | E20: Reordenar campos y advertir antes de modificar o borrar campos que ya tienen datos. | F20: • El orden nuevo se conserva al volver a entrar. • Antes de un cambio riesgoso aparece una advertencia que indica qué datos se afectan. | G20: =COUNTIF(Tareas!$C$10:$C$400,"H-12 · Cambios seguros en la estructura") | H20: =COUNTIFS(Tareas!$C$10:$C$400,"H-12 · Cambios seguros en la estructura",Tareas!$J$10:$J$400,"Hecho") | I20: ENS-019, ENS-020 | J20: Protege los datos cuando el sistema ya se usa a diario.
A21: H-13 | B21: MVP 3 | C21: Usar | D21: Borrador y versión publicada | E21: Modificar el sistema en borrador sin alterar lo que se está usando, y publicar cuando esté listo. | F21: • Los cambios en borrador no afectan el modo usar. • Al publicar se aplican todos los cambios juntos. | G21: =COUNTIF(Tareas!$C$10:$C$400,"H-13 · Borrador y versión publicada") | H21: =COUNTIFS(Tareas!$C$10:$C$400,"H-13 · Borrador y versión publicada",Tareas!$J$10:$J$400,"Hecho") | I21: ENS-052 | J21: Necesario cuando hay datos reales en uso; evolución del modo construir/usar.
A22: H-14 | B22: MVP 3 | C22: Consultar | D22: Personalización de columnas (computadora y celular) | E22: Elegir qué columnas mostrar en la tabla, con una configuración distinta para celular. | F22: • Ocultar/mostrar columnas no borra información. • La configuración móvil no modifica la de computadora. • La ficha sigue mostrando todo aunque haya columnas ocultas. | G22: =COUNTIF(Tareas!$C$10:$C$400,"H-14 · Personalización de columnas (computadora y celular)") | H22: =COUNTIFS(Tareas!$C$10:$C$400,"H-14 · Personalización de columnas (computadora y celular)",Tareas!$J$10:$J$400,"Hecho") | I22: ENS-032, ENS-037 | J22: Mejora de uso; la tabla del core ya funciona sin esto.
A23: H-16 | B23: MVP 3 | C23: Indicadores | D23: Panel de indicadores y gráficos básicos | E23: Mostrar un resumen de actividad (registros por bloque) y gráficos simples con los datos cargados. | F23: • Se ve la cantidad de registros por bloque y se actualiza. • Los gráficos usan datos reales y avisan si no hay información. | G23: =COUNTIF(Tareas!$C$10:$C$400,"H-16 · Panel de indicadores y gráficos básicos") | H23: =COUNTIFS(Tareas!$C$10:$C$400,"H-16 · Panel de indicadores y gráficos básicos",Tareas!$J$10:$J$400,"Hecho") | I23: ENS-045, ENS-048 | J23: Suma valor percibido, pero no es imprescindible para mostrar el core.
A24: H-17 | B24: MVP 3 | C24: Usar | D24: Tutorial inicial y ayuda | E24: Un recorrido breve que enseñe a subir la foto, revisar y consultar, y una sección de ayuda siempre a mano. | F24: • El tutorial muestra el flujo foto → revisar → consultar y se puede saltear. • Se puede volver a abrir desde ayuda. | G24: =COUNTIF(Tareas!$C$10:$C$400,"H-17 · Tutorial inicial y ayuda") | H24: =COUNTIFS(Tareas!$C$10:$C$400,"H-17 · Tutorial inicial y ayuda",Tareas!$J$10:$J$400,"Hecho") | I24: ENS-040 | J24: El core ya es guiado; el tutorial suma una vez validado con usuarios.
A25: H-18 | B25: MVP 3 | C25: Calidad | D25: Respaldos y monitoreo de errores | E25: Tener copias de seguridad recuperables y registrar errores para corregirlos. | F25: • Se hace una copia y se comprueba que los datos se restauran. • Los errores quedan registrados sin guardar contraseñas ni datos sensibles. | G25: =COUNTIF(Tareas!$C$10:$C$400,"H-18 · Respaldos y monitoreo de errores") | H25: =COUNTIFS(Tareas!$C$10:$C$400,"H-18 · Respaldos y monitoreo de errores",Tareas!$J$10:$J$400,"Hecho") | I25: ENS-067, ENS-068 | J25: Operación estable cuando hay usuarios reales cargando datos.
A26: H-15 | B26: MVP 4 | C26: Conectar | D26: Importar y exportar datos (CSV / planilla) | E26: Subir datos existentes desde una planilla relacionando columnas con campos, y exportar los registros a CSV. | F26: • Antes de importar se mapean columnas a campos. • Los datos se importan/exportan sin mezclar negocios ni campos. | G26: =COUNTIF(Tareas!$C$10:$C$400,"H-15 · Importar y exportar datos (CSV / planilla)") | H26: =COUNTIFS(Tareas!$C$10:$C$400,"H-15 · Importar y exportar datos (CSV / planilla)",Tareas!$J$10:$J$400,"Hecho") | I26: ENS-034, ENS-054 | J26: El público objetivo no usa planillas: la entrada principal es la foto. Queda para negocios que migren desde Excel.
A27: H-19 | B27: MVP 4 | C27: Colaborar | D27: Equipos: espacios, roles e invitaciones | E27: Manejar varios negocios desde una cuenta, invitar colaboradores con roles (configura / usa), entrar por enlace propio y auditar cambios. | F27: • Los datos mostrados siempre pertenecen al negocio seleccionado. • Solo un usuario autorizado invita y asigna permisos. • El enlace lleva al proyecto correcto y respeta el acceso. • Queda registrado quién, cuándo y qué cambió. | G27: =COUNTIF(Tareas!$C$10:$C$400,"H-19 · Equipos: espacios, roles e invitaciones") | H27: =COUNTIFS(Tareas!$C$10:$C$400,"H-19 · Equipos: espacios, roles e invitaciones",Tareas!$J$10:$J$400,"Hecho") | I27: ENS-009, ENS-042, ENS-043, ENS-044, ENS-053 | J27: Permisos granulares de varios empleados quedan fuera del MVP según la propuesta.
A28: H-20 | B28: MVP 4 | C28: Planes | D28: Planes, prueba premium y control por plan | E28: Mostrar plan gratuito y premium, ofrecer prueba de 7 días y habilitar funciones según el plan. | F28: • La persona entiende qué incluye cada plan. • Se registra inicio y fin de la prueba. • Las funciones premium no se habilitan sin el plan. | G28: =COUNTIF(Tareas!$C$10:$C$400,"H-20 · Planes, prueba premium y control por plan") | H28: =COUNTIFS(Tareas!$C$10:$C$400,"H-20 · Planes, prueba premium y control por plan",Tareas!$J$10:$J$400,"Hecho") | I28: ENS-059, ENS-060, ENS-061 | J28: Monetización: llega cuando el producto ya demostró valor.
A29: H-21 | B29: MVP 4 | C29: Planes | D29: Administración de organizaciones (backoffice) | E29: Buscar y consultar negocios desde la administración interna de Ensambla. | F29: • Se pueden buscar negocios y ver su situación (plan, uso). | G29: =COUNTIF(Tareas!$C$10:$C$400,"H-21 · Administración de organizaciones (backoffice)") | H29: =COUNTIFS(Tareas!$C$10:$C$400,"H-21 · Administración de organizaciones (backoffice)",Tareas!$J$10:$J$400,"Hecho") | I29: ENS-063 | J29: Herramienta interna; se necesita al haber planes y clientes.
A30: H-22 | B30: MVP 4 | C30: Indicadores | D30: Inventario, costos y reportes | E30: Calcular stock por entradas/salidas, costo de fabricación de productos y generar reportes descargables con filtros. | F30: • Las entradas y salidas actualizan el stock. • El costo usa cantidades, precios y unidades. • Los totales del reporte coinciden con los filtros y no muestran otros negocios. | G30: =COUNTIF(Tareas!$C$10:$C$400,"H-22 · Inventario, costos y reportes") | H30: =COUNTIFS(Tareas!$C$10:$C$400,"H-22 · Inventario, costos y reportes",Tareas!$J$10:$J$400,"Hecho") | I30: ENS-046, ENS-047, ENS-049 | J30: Analítica avanzada, fuera del MVP inicial según la propuesta.
A31: H-23 | B31: MVP 4 | C31: Cargar datos | D31: Adjuntar archivos a registros | E31: Agregar fotos o documentos a un registro. | F31: • El archivo queda en el registro correcto y se controlan tamaño y tipo. | G31: =COUNTIF(Tareas!$C$10:$C$400,"H-23 · Adjuntar archivos a registros") | H31: =COUNTIFS(Tareas!$C$10:$C$400,"H-23 · Adjuntar archivos a registros",Tareas!$J$10:$J$400,"Hecho") | I31: ENS-027 | J31: El almacenamiento ya existe desde MVP 2 (fotos del cuaderno); acá se suma como tipo de campo con límites por plan.
A32: H-24 | B32: MVP 4 | C32: Conectar | D32: Formularios compartibles | E32: Compartir un formulario para que personas externas lo completen. | F32: • El dueño habilita/deshabilita el formulario y define qué datos pide. | G32: =COUNTIF(Tareas!$C$10:$C$400,"H-24 · Formularios compartibles") | H32: =COUNTIFS(Tareas!$C$10:$C$400,"H-24 · Formularios compartibles",Tareas!$J$10:$J$400,"Hecho") | I32: ENS-058 | J32: Expone datos hacia afuera: va con permisos y planes resueltos.
A33: H-25 | B33: MVP 4 | C33: Conectar | D33: Automatizaciones: alertas, API y webhooks | E33: Recibir avisos automáticos según condiciones y conectar otras herramientas por API/webhooks. | F33: • Se elige condición y destinatario y el aviso llega al cumplirse. • La API tiene reglas de acceso y eventos documentados. | G33: =COUNTIF(Tareas!$C$10:$C$400,"H-25 · Automatizaciones: alertas, API y webhooks") | H33: =COUNTIFS(Tareas!$C$10:$C$400,"H-25 · Automatizaciones: alertas, API y webhooks",Tareas!$J$10:$J$400,"Hecho") | I33: ENS-056, ENS-057 | J33: Automatizaciones complejas quedan fuera del MVP inicial según la propuesta.
A34: H-26 | B34: MVP 4 | C34: Conectar | D34: Integración con Mercado Libre | E34: Conectar la información de Mercado Libre con el negocio. | F34: • La persona autoriza la conexión y puede revocarla cuando quiera. | G34: =COUNTIF(Tareas!$C$10:$C$400,"H-26 · Integración con Mercado Libre") | H34: =COUNTIFS(Tareas!$C$10:$C$400,"H-26 · Integración con Mercado Libre",Tareas!$J$10:$J$400,"Hecho") | I34: ENS-055 | J34: Integración comercial: función premium de la versión completa.
A35: H-27 | B35: MVP 4 | C35: Planes | D35: Marketplace de plantillas | E35: Explorar y publicar plantillas hechas por terceros. | F35: • Las plantillas publicadas pasan por revisión previa. | G35: =COUNTIF(Tareas!$C$10:$C$400,"H-27 · Marketplace de plantillas") | H35: =COUNTIFS(Tareas!$C$10:$C$400,"H-27 · Marketplace de plantillas",Tareas!$J$10:$J$400,"Hecho") | I35: ENS-062 | J35: Vía de ingresos posterior según el modelo de negocio.
A36: H-31 | B36: MVP 4 | C36: Digitalizar | D36: Cargar por WhatsApp o audio | E36: Enviar fotos del cuaderno por WhatsApp o dictar una venta o gasto por audio, y que entre al mismo flujo de revisión. | F36: • Una foto enviada al número de Ensambla llega al negocio correcto y queda para revisar. • Un audio se transcribe y se convierte en un registro a confirmar. | G36: =COUNTIF(Tareas!$C$10:$C$400,"H-31 · Cargar por WhatsApp o audio") | H36: =COUNTIFS(Tareas!$C$10:$C$400,"H-31 · Cargar por WhatsApp o audio",Tareas!$J$10:$J$400,"Hecho") | I36: Nuevo (v1.1) | J36: Acerca la carga a herramientas que el público ya usa; depende del core de IA y de planes resueltos.

Sheet Trazabilidad
A1: TRAZABILIDAD · backlog anterior → historia nueva (v1.1: reenfoque en digitalización de cuadernos con IA)
A3: Código anterior | B3: Funcionalidad anterior | C3: Prioridad anterior | D3: Historia nueva | E3: MVP
A4: ENS-001 | B4: Registro de cuenta | C4: MVP | D4: H-01 · Acceso y sesión | E4: MVP 2
A5: ENS-002 | B5: Inicio de sesión | C5: MVP | D5: H-01 · Acceso y sesión | E5: MVP 2
A6: ENS-003 | B6: Cerrar sesión | C6: MVP | D6: H-01 · Acceso y sesión | E6: MVP 2
A7: ENS-004 | B7: Recuperación de contraseña | C7: Después | D7: H-10 · Gestión de cuenta y negocio | E7: MVP 3
A8: ENS-005 | B8: Protección de rutas y sesiones | C8: MVP | D8: H-01 · Acceso y sesión | E8: MVP 2
A9: ENS-006 | B9: Crear espacio de negocio | C9: MVP | D9: H-02 · Espacio de negocio y aislamiento de datos | E9: MVP 2
A10: ENS-007 | B10: Editar datos del negocio | C10: MVP | D10: H-10 · Gestión de cuenta y negocio | E10: MVP 3
A11: ENS-008 | B11: Estado inicial guiado | C11: MVP | D11: H-03 · Crear proyecto desde plantilla o en blanco | E11: MVP 2
A12: ENS-009 | B12: Cambiar entre espacios | C12: Después | D12: H-19 · Equipos: espacios, roles e invitaciones | E12: MVP 4
A13: ENS-010 | B13: Catálogo de plantillas | C13: MVP | D13: H-03 · Crear proyecto desde plantilla o en blanco | E13: MVP 2
A14: ENS-011 | B14: Vista previa de plantilla | C14: MVP | D14: H-11 · Plantillas y proyectos: vista previa y duplicado | E14: MVP 3
... A78: NUEVO-07 | B78: Carga por WhatsApp o audio | C78: — (v1.1) | D78: H-31 · Cargar por WhatsApp o audio | E78: MVP 4
